odoo8_addon_pos_to_weight_by_product_uom-8.0.1.0.0-py2.7-nspkg.pth
odoo8_addon_pos_to_weight_by_product_uom-8.0.1.0.0.dist-info/DESCRIPTION.rst
odoo8_addon_pos_to_weight_by_product_uom-8.0.1.0.0.dist-info/METADATA
odoo8_addon_pos_to_weight_by_product_uom-8.0.1.0.0.dist-info/RECORD
odoo8_addon_pos_to_weight_by_product_uom-8.0.1.0.0.dist-info/WHEEL
odoo8_addon_pos_to_weight_by_product_uom-8.0.1.0.0.dist-info/metadata.json
odoo8_addon_pos_to_weight_by_product_uom-8.0.1.0.0.dist-info/namespace_packages.txt
odoo8_addon_pos_to_weight_by_product_uom-8.0.1.0.0.dist-info/top_level.txt
odoo_addons/pos_to_weight_by_product_uom/README.rst
odoo_addons/pos_to_weight_by_product_uom/__init__.py
odoo_addons/pos_to_weight_by_product_uom/__openerp__.py
odoo_addons/pos_to_weight_by_product_uom/demo/product_uom_categ_demo.xml
odoo_addons/pos_to_weight_by_product_uom/demo/product_uom_demo.xml
odoo_addons/pos_to_weight_by_product_uom/i18n/fr.po
odoo_addons/pos_to_weight_by_product_uom/models/__init__.py
odoo_addons/pos_to_weight_by_product_uom/models/product_template.py
odoo_addons/pos_to_weight_by_product_uom/models/product_uom.py
odoo_addons/pos_to_weight_by_product_uom/models/product_uom_categ.py
odoo_addons/pos_to_weight_by_product_uom/static/description/icon.png
odoo_addons/pos_to_weight_by_product_uom/static/description/uom_categ_button_toweigh.png
odoo_addons/pos_to_weight_by_product_uom/static/description/uom_categ_change_toweigh.png
odoo_addons/pos_to_weight_by_product_uom/static/description/uom_categ_toweigh.png
odoo_addons/pos_to_weight_by_product_uom/static/description/uom_change_toweigh.png
odoo_addons/pos_to_weight_by_product_uom/static/description/uom_pos_change_toweigh.png
odoo_addons/pos_to_weight_by_product_uom/static/description/uom_pos_change_toweigh_checked.png
odoo_addons/pos_to_weight_by_product_uom/static/description/uom_toweigh.png
odoo_addons/pos_to_weight_by_product_uom/views/pos_to_weight.xml
