Metadata-Version: 2.0
Name: odoo8-addon-pos-to-weight-by-product-uom
Version: 8.0.1.0.0
Summary: Module summary
Home-page: https://github.com/OCA/pos
Author: GRAP, Odoo Community Association (OCA)
Author-email: support@odoo-community.org
License: AGPL-3
Platform: UNKNOWN
Classifier: Programming Language :: Python
Classifier: Framework :: Odoo
Classifier: License :: OSI Approved :: GNU Affero General Public License v3
Requires-Python: ~=2.7
Requires-Dist: odoo (<9.0a,>=8.0a)
